odoo/addons/l10n_es_intrastat_report/README.rst
odoo/addons/l10n_es_intrastat_report/__init__.py
odoo/addons/l10n_es_intrastat_report/__manifest__.py
odoo/addons/l10n_es_intrastat_report/hooks.py
odoo/addons/l10n_es_intrastat_report/data/Estruc_NC2023.xlsx
odoo/addons/l10n_es_intrastat_report/data/NC_20.xls
odoo/addons/l10n_es_intrastat_report/data/account_fiscal_position_template.xml
odoo/addons/l10n_es_intrastat_report/data/intrastat_transaction.xml
odoo/addons/l10n_es_intrastat_report/i18n/ca.po
odoo/addons/l10n_es_intrastat_report/i18n/es.po
odoo/addons/l10n_es_intrastat_report/i18n/l10n_es_intrastat_report.pot
odoo/addons/l10n_es_intrastat_report/migrations/14.0.1.0.0/pre-migration.py
odoo/addons/l10n_es_intrastat_report/models/__init__.py
odoo/addons/l10n_es_intrastat_report/models/l10n_es_intrastat_product_declaration.py
odoo/addons/l10n_es_intrastat_report/models/stock_location.py
odoo/addons/l10n_es_intrastat_report/readme/CONFIGURE.rst
odoo/addons/l10n_es_intrastat_report/readme/CONTRIBUTORS.rst
odoo/addons/l10n_es_intrastat_report/readme/DESCRIPTION.rst
odoo/addons/l10n_es_intrastat_report/readme/INSTALL.rst
odoo/addons/l10n_es_intrastat_report/readme/ROADMAP.rst
odoo/addons/l10n_es_intrastat_report/readme/USAGE.rst
odoo/addons/l10n_es_intrastat_report/report/__init__.py
odoo/addons/l10n_es_intrastat_report/report/intrastat_product_report_xls.py
odoo/addons/l10n_es_intrastat_report/security/ir.model.access.csv
odoo/addons/l10n_es_intrastat_report/security/l10n_es_intrastat_report_security.xml
odoo/addons/l10n_es_intrastat_report/static/description/icon.png
odoo/addons/l10n_es_intrastat_report/static/description/index.html
odoo/addons/l10n_es_intrastat_report/tests/__init__.py
odoo/addons/l10n_es_intrastat_report/tests/test_l10n_es_intrastat_report.py
odoo/addons/l10n_es_intrastat_report/views/l10n_es_intrastat_product.xml
odoo/addons/l10n_es_intrastat_report/wizards/__init__.py
odoo/addons/l10n_es_intrastat_report/wizards/l10n_es_intrastat_code_import.py
odoo14_addon_l10n_es_intrastat_report-14.0.4.1.0.dist-info/METADATA
odoo14_addon_l10n_es_intrastat_report-14.0.4.1.0.dist-info/WHEEL
odoo14_addon_l10n_es_intrastat_report-14.0.4.1.0.dist-info/top_level.txt
odoo14_addon_l10n_es_intrastat_report-14.0.4.1.0.dist-info/RECORD
